ChangeLog
LICENSE
MANIFEST.in
README.md
README.rst
setup.py
testWrite.py
doc/index.html
doc/nonblock.BackgroundRead.html
doc/nonblock.BackgroundWrite.html
doc/nonblock.common.html
doc/nonblock.html
doc/nonblock.read.html
example/simpleGame.py
nonblock/BackgroundRead.py
nonblock/BackgroundWrite.py
nonblock/__init__.py
nonblock/common.py
nonblock/read.py
python_nonblock.egg-info/PKG-INFO
python_nonblock.egg-info/SOURCES.txt
python_nonblock.egg-info/dependency_links.txt
python_nonblock.egg-info/top_level.txt