Metadata-Version: 1.1
Name: python-nonblock
Version: 4.0.0
Summary: Pure-Python non-blocking IO functions
Home-page: https://github.com/kata198/python-nonblock
Author: Tim Savannah
Author-email: kata198@gmail.com
License: LGPLv2
Keywords: python,nonblock,nonblocking,io,blocking,non,read,read1,file,stream,pure,function
Platform: UNKNOWN
Classifier: Development Status :: 5 - Production/Stable
Classifier: Programming Language :: Python
Classifier: License :: OSI Approved :: GNU Lesser General Public License v2 (LGPLv2)
Classifier: Programming Language :: Python :: 2
Classifier: Programming Language :: Python :: 2.7
Classifier: Programming Language :: Python :: 3
Classifier: Programming Language :: Python :: 3.4
Classifier: Programming Language :: Python :: 3.5
Classifier: Operating System :: POSIX
Classifier: Operating System :: POSIX :: Linux
Classifier: Operating System :: Unix
Classifier: Operating System :: Microsoft :: Windows
Classifier: Topic :: System
